target_s3_csv/__init__.py
target_s3_csv/s3.py
target_s3_csv/utils.py
pipelinewise_target_s3_csv-2.0.0.dist-info/LICENSE
pipelinewise_target_s3_csv-2.0.0.dist-info/METADATA
pipelinewise_target_s3_csv-2.0.0.dist-info/WHEEL
pipelinewise_target_s3_csv-2.0.0.dist-info/entry_points.txt
pipelinewise_target_s3_csv-2.0.0.dist-info/top_level.txt
pipelinewise_target_s3_csv-2.0.0.dist-info/RECORD
