Metadata-Version: 2.1
Name: pipelinewise-target-s3-csv
Version: 2.0.0
Summary: Singer.io target for writing CSV files and upload to S3 - PipelineWise compatible
Home-page: https://github.com/transferwise/pipelinewise-target-s3-csv
Author: Wise
License: UNKNOWN
Platform: UNKNOWN
Classifier: License :: OSI Approved :: Apache Software License
Classifier: Programming Language :: Python :: 3 :: Only
Classifier: Programming Language :: Python :: 3.7
Classifier: Programming Language :: Python :: 3.8
Classifier: Programming Language :: Python :: 3.9
Classifier: Programming Language :: Python :: 3.10
Requires-Python: >=3.7.0, <3.11
Requires-Dist: pipelinewise-singer-python (==1.*)
Requires-Dist: inflection (==0.5.1)
Requires-Dist: boto3 (==1.17.39)
Provides-Extra: test
Requires-Dist: pylint (==2.10.*) ; extra == 'test'
Requires-Dist: pytest (==6.2.*) ; extra == 'test'
Requires-Dist: pytest-cov (==2.12.*) ; extra == 'test'
